emplace/__init__.py
emplace/formatter.py
emplace/placeholder.py
emplace-0.1.0.dist-info/METADATA
emplace-0.1.0.dist-info/WHEEL
emplace-0.1.0.dist-info/RECORD
