Metadata-Version: 2.3
Name: emplace
Version: 0.1.0
Summary: Modern and easy way to handle placeholders.
License: MIT
Author: EeeMoon
Requires-Python: >=3.10,<4.0
Classifier: License :: OSI Approved :: MIT License
Classifier: Programming Language :: Python :: 3
Classifier: Programming Language :: Python :: 3.10
Classifier: Programming Language :: Python :: 3.11
Classifier: Programming Language :: Python :: 3.12
Classifier: Programming Language :: Python :: 3.13
Project-URL: Homepage, https://github.com/eeemoon/emplace
